pytip/__init__.py
pytip/__main__.py
pytip/conftest.py
pytip/tips.py
pybites_tips-1.1.0.dist-info/LICENSE
pybites_tips-1.1.0.dist-info/METADATA
pybites_tips-1.1.0.dist-info/WHEEL
pybites_tips-1.1.0.dist-info/entry_points.txt
pybites_tips-1.1.0.dist-info/top_level.txt
pybites_tips-1.1.0.dist-info/RECORD
