Metadata-Version: 2.1
Name: pybites-tips
Version: 1.1.0
Summary: Read PyBites Python tips from the command line
Home-page: https://github.com/PyBites-Open-Source/pybites-tips
Author: PyBites
Author-email: support@pybit.es
License: MIT
Classifier: License :: OSI Approved :: MIT License
Classifier: Programming Language :: Python :: 3
Classifier: Programming Language :: Python :: 3.8
License-File: LICENSE
Requires-Dist: requests
